stsff_automation/__init__.py
stsff_automation/generate_description.py
stsff_automation/utils.py
stsff_automation/vcs_info.py
stsff_automation-1.0.7.dist-info/METADATA
stsff_automation-1.0.7.dist-info/WHEEL
stsff_automation-1.0.7.dist-info/entry_points.txt
stsff_automation-1.0.7.dist-info/top_level.txt
stsff_automation-1.0.7.dist-info/RECORD
