Metadata-Version: 2.1
Name: stsff-automation
Version: 1.0.7
Summary: A Python library with some stsff stuff for automation, utils, vcs_info, helpers, build systems and etc
Home-page: https://git.flightfactor.aero/dev-ops/stsff-automation-lib-py
Author: StepToSky & FlightFactor
Author-email: technical@flightfactor.aero
License: UNKNOWN
Platform: UNKNOWN
Classifier: Programming Language :: Python :: 3
Classifier: License :: Other/Proprietary License
Classifier: Operating System :: OS Independent
Classifier: Topic :: Utilities
Classifier: Development Status :: 4 - Beta
Requires-Dist: semantic-version (<3,>=2)
